aipoincare/__init__.py
aipoincare/main.py
aipoincare/backend/__init__.py
aipoincare/backend/training.py
aipoincare/backend/data/__init__.py
aipoincare/backend/data/double_pendulum
aipoincare/backend/data/magnetic_mirror
aipoincare/backend/data/oned_harmonic
aipoincare/backend/data/three_body
aipoincare/backend/data/twod_kepler
aipoincare/backend/models/__init__.py
aipoincare/static/__init__.py
aipoincare/static/css/__init__.py
aipoincare/static/fonts/__init__.py
aipoincare/static/images/__init__.py
aipoincare/static/js/__init__.py
aipoincare/templates/__init__.py
aipoincare/templates/home.html
aipoincare/templates/index.html
aipoincare-0.1.5.dist-info/LICENSE
aipoincare-0.1.5.dist-info/METADATA
aipoincare-0.1.5.dist-info/WHEEL
aipoincare-0.1.5.dist-info/top_level.txt
aipoincare-0.1.5.dist-info/RECORD
